dapr/__init__.py
dapr/proto/__init__.py
dapr/proto/common/__init__.py
dapr/proto/common/v1/__init__.py
dapr/proto/common/v1/common_pb2.py
dapr/proto/common/v1/common_pb2_grpc.py
dapr/proto/dapr/__init__.py
dapr/proto/dapr/v1/__init__.py
dapr/proto/dapr/v1/dapr_pb2.py
dapr/proto/dapr/v1/dapr_pb2_grpc.py
dapr/proto/daprclient/__init__.py
dapr/proto/daprclient/v1/__init__.py
dapr/proto/daprclient/v1/daprclient_pb2.py
dapr/proto/daprclient/v1/daprclient_pb2_grpc.py
dapr_client-0.4.0b1.dist-info/LICENSE
dapr_client-0.4.0b1.dist-info/METADATA
dapr_client-0.4.0b1.dist-info/WHEEL
dapr_client-0.4.0b1.dist-info/top_level.txt
dapr_client-0.4.0b1.dist-info/RECORD
