Metadata-Version: 2.1
Name: dapr-client
Version: 0.4.0b1
Summary: Dapr client sdk using gRPC.
Home-page: https://dapr.io/
Author: dapr.io
Author-email: pypidapr@microsoft.com
License: UNKNOWN
Platform: UNKNOWN
Classifier: Programming Language :: Python :: 3
Classifier: License :: OSI Approved :: MIT License
Classifier: Operating System :: OS Independent
Requires-Python: >=3.6
Requires-Dist: protobuf
Requires-Dist: grpcio
